macmenuqbt/__init__.py
macmenuqbt/core.py
macmenuqbt/ee1.py
macmenuqbt/ee2.py
macmenuqbt/ee3.py
macmenuqbt/ee4.py
macmenuqbt/sorting_options.py
macmenuqbt/utils.py
macmenuqbt/icon/__init__.py
macmenuqbt/icon/color.png
macmenuqbt/icon/dark.png
macmenuqbt/icon/light.png
macmenuqbt/icon/warning_color.png
macmenuqbt-0.3.0.dist-info/licenses/LICENSE
plugins/telegram_notify.py
plugins/template.py
plugins/trqbt.py
macmenuqbt-0.3.0.dist-info/METADATA
macmenuqbt-0.3.0.dist-info/WHEEL
macmenuqbt-0.3.0.dist-info/entry_points.txt
macmenuqbt-0.3.0.dist-info/top_level.txt
macmenuqbt-0.3.0.dist-info/RECORD
