Metadata-Version: 2.4
Name: macmenuqbt
Version: 0.3.0
Summary: macOS menu bar app to show qBittorrent torrents status.
Author-email: Julien Minniti <minnitijulien06@gmail.com>
License-Expression: MIT
Project-URL: Homepage, https://github.com/Jumitti/MacMenu-qBittorrent
Requires-Python: >=3.8
License-File: LICENSE
Requires-Dist: qbittorrent-api
Requires-Dist: rumps
Requires-Dist: PyQt5
Requires-Dist: pyobjc
Requires-Dist: pyobjc-framework-quartz
Dynamic: license-file
